odoo9_addon_membership_variable_period-9.0.1.0.0.99.dev10-py2.7-nspkg.pth
odoo9_addon_membership_variable_period-9.0.1.0.0.99.dev10.dist-info/DESCRIPTION.rst
odoo9_addon_membership_variable_period-9.0.1.0.0.99.dev10.dist-info/METADATA
odoo9_addon_membership_variable_period-9.0.1.0.0.99.dev10.dist-info/RECORD
odoo9_addon_membership_variable_period-9.0.1.0.0.99.dev10.dist-info/WHEEL
odoo9_addon_membership_variable_period-9.0.1.0.0.99.dev10.dist-info/metadata.json
odoo9_addon_membership_variable_period-9.0.1.0.0.99.dev10.dist-info/namespace_packages.txt
odoo9_addon_membership_variable_period-9.0.1.0.0.99.dev10.dist-info/top_level.txt
odoo_addons/membership_variable_period/README.rst
odoo_addons/membership_variable_period/__init__.py
odoo_addons/membership_variable_period/__openerp__.py
odoo_addons/membership_variable_period/data/membership_data.xml
odoo_addons/membership_variable_period/i18n/de.po
odoo_addons/membership_variable_period/i18n/es.po
odoo_addons/membership_variable_period/i18n/membership_variable_period.pot
odoo_addons/membership_variable_period/i18n/sl.po
odoo_addons/membership_variable_period/models/__init__.py
odoo_addons/membership_variable_period/models/account_invoice.py
odoo_addons/membership_variable_period/models/product_template.py
odoo_addons/membership_variable_period/models/res_partner.py
odoo_addons/membership_variable_period/static/description/icon.png
odoo_addons/membership_variable_period/static/description/icon.svg
odoo_addons/membership_variable_period/static/description/icon_main.svg
odoo_addons/membership_variable_period/tests/__init__.py
odoo_addons/membership_variable_period/tests/test_membership_variable_period.py
odoo_addons/membership_variable_period/views/product_template_views.xml
odoo_addons/membership_variable_period/views/res_partner_views.xml
